regdown/__init__.py
regdown/tests.py
regdown-1.0.7.dist-info/LICENSE
regdown-1.0.7.dist-info/METADATA
regdown-1.0.7.dist-info/WHEEL
regdown-1.0.7.dist-info/top_level.txt
regdown-1.0.7.dist-info/RECORD
