Metadata-Version: 2.1
Name: regdown
Version: 1.0.7
Summary: Markdown extension for interactive regulations
Author-email: CFPB <tech@cfpb.gov>
License: CC0
Project-URL: Homepage, https://github.com/cfpb/regdown
Project-URL: Bug Reports, https://github.com/cfpb/regdown/issues
Project-URL: Source, https://github.com/cfpb/regdown
Classifier: License :: CC0 1.0 Universal (CC0 1.0) Public Domain Dedication
Classifier: License :: Public Domain
Classifier: Programming Language :: Python
Classifier: Programming Language :: Python :: 3
Requires-Python: >=3.8
License-File: LICENSE
Requires-Dist: Markdown (>=3.4)
